thule.py
thule-1.0.dist-info/LICENSE.txt
thule-1.0.dist-info/METADATA
thule-1.0.dist-info/WHEEL
thule-1.0.dist-info/top_level.txt
thule-1.0.dist-info/RECORD
