Metadata-Version: 2.1
Name: thule
Version: 1.0
Summary: Module to facilitate actions on a file tree.
Home-page: https://github.com/cjengdahl/thule
Author: Cory Engdahl
Author-email: cjengdahl@gmail.com
License: MIT
Keywords: file walker
License-File: LICENSE.txt
